django_social_share/__init__.py
django_social_share/models.py
django_social_share/views.py
django_social_share/templates/django_social_share/templatetags/copy_script.html
django_social_share/templates/django_social_share/templatetags/copy_to_clipboard.html
django_social_share/templates/django_social_share/templatetags/pinterest_script.html
django_social_share/templates/django_social_share/templatetags/post_to_facebook.html
django_social_share/templates/django_social_share/templatetags/post_to_gplus.html
django_social_share/templates/django_social_share/templatetags/post_to_linkedin.html
django_social_share/templates/django_social_share/templatetags/post_to_reddit.html
django_social_share/templates/django_social_share/templatetags/post_to_telegram.html
django_social_share/templates/django_social_share/templatetags/post_to_twitter.html
django_social_share/templates/django_social_share/templatetags/post_to_whatsapp.html
django_social_share/templates/django_social_share/templatetags/save_to_pinterest.html
django_social_share/templates/django_social_share/templatetags/send_email.html
django_social_share/templatetags/__init__.py
django_social_share/templatetags/social_share.py
django_social_share/tests/__init__.py
django_social_share/tests/runtests.py
django_social_share/tests/tests.py
django_social_share-2.3.0.dist-info/LICENSE
django_social_share-2.3.0.dist-info/METADATA
django_social_share-2.3.0.dist-info/WHEEL
django_social_share-2.3.0.dist-info/top_level.txt
django_social_share-2.3.0.dist-info/RECORD
