Metadata-Version: 1.1
Name: django-social-share
Version: 2.3.0
Summary: Templatetags for 'tweet this' and 'share on facebook'
Home-page: https://github.com/fcurella/django-social-share
Author: Flavio Curella
Author-email: flavio.curella@curella.org
License: MIT
Platform: UNKNOWN
Classifier: Development Status :: 3 - Alpha
Classifier: Environment :: Console
Classifier: Intended Audience :: Developers
Classifier: Intended Audience :: Information Technology
Classifier: License :: OSI Approved :: MIT License
Classifier: Operating System :: OS Independent
Classifier: Programming Language :: Python
Classifier: Framework :: Django
